.DS_Store
.gitattributes
.gitignore
LICENSE
README.md
__init__.py
changelog.md
setup.py
supreme_spoon/.DS_Store
supreme_spoon/__init__.py
supreme_spoon/extra_functions.py
supreme_spoon/fit_lightcurves.py
supreme_spoon/fit_lightcurves.yaml
supreme_spoon/plotting.py
supreme_spoon/run_DMS.py
supreme_spoon/run_DMS.yaml
supreme_spoon/stage1.py
supreme_spoon/stage2.py
supreme_spoon/stage3.py
supreme_spoon/stage4.py
supreme_spoon/utils.py
supreme_spoon.egg-info/PKG-INFO
supreme_spoon.egg-info/SOURCES.txt
supreme_spoon.egg-info/dependency_links.txt
supreme_spoon.egg-info/requires.txt
supreme_spoon.egg-info/top_level.txt