Metadata-Version: 2.1
Name: supreme-spoon
Version: 1.3.1
Summary: Tools for Reduction of NIRISS/SOSS TSOs
Home-page: https://github.com/radicamc/supreme-spoon
Author: Michael Radica
Author-email: michael.radica@umontreal.ca
License: MIT
Classifier: Development Status :: 3 - Alpha
Classifier: Intended Audience :: Science/Research
Classifier: License :: OSI Approved :: MIT License
Classifier: Operating System :: OS Independent
Classifier: Programming Language :: Python :: 3.10
License-File: LICENSE
Requires-Dist: applesoss==2.0.2
Requires-Dist: astropy
Requires-Dist: astroquery
Requires-Dist: bottleneck
Requires-Dist: corner
Requires-Dist: jwst==1.12.5
Requires-Dist: matplotlib
Requires-Dist: more_itertools
Requires-Dist: numpy
Requires-Dist: pandas
Requires-Dist: ray
Requires-Dist: scikit-learn
Requires-Dist: scipy
Requires-Dist: tqdm
Requires-Dist: pastasoss
Requires-Dist: pyyaml
Provides-Extra: stage4
Requires-Dist: supreme_spoon; extra == "stage4"
Requires-Dist: cython; extra == "stage4"
Requires-Dist: dynesty==1.2.2; extra == "stage4"
Requires-Dist: exotic_ld; extra == "stage4"
Requires-Dist: h5py; extra == "stage4"
Requires-Dist: juliet; extra == "stage4"
Provides-Extra: webbpsf
Requires-Dist: supreme_spoon; extra == "webbpsf"
Requires-Dist: webbpsf>=1.1.1; extra == "webbpsf"
